intellifs/__init__.py
intellifs/__main__.py
intellifs/embedder.py
intellifs/indexables.py
intellifs/settings.py
intellifs-0.0.1.dist-info/entry_points.txt
intellifs-0.0.1.dist-info/LICENSE
intellifs-0.0.1.dist-info/METADATA
intellifs-0.0.1.dist-info/WHEEL
intellifs-0.0.1.dist-info/RECORD
