Metadata-Version: 2.1
Name: intellifs
Version: 0.0.1
Summary: Content-Aware File System.
License: MIT
Author: Harsh Verma
Author-email: synacktra.work@gmail.com
Requires-Python: >=3.9.0,<3.12
Classifier: License :: OSI Approved :: MIT License
Classifier: Programming Language :: Python :: 3
Classifier: Programming Language :: Python :: 3.9
Classifier: Programming Language :: Python :: 3.10
Classifier: Programming Language :: Python :: 3.11
Requires-Dist: cyclopts (==2.1.2)
Requires-Dist: fastembed (==0.1.3)
Requires-Dist: minifzf (==0.1.4)
Requires-Dist: qdrant-client (==1.7.2)
Requires-Dist: rich (==13.7.0)
Requires-Dist: unstructured[pdf] (==0.12.0)
